yuhanbolh/__init__.py
yuhanbolh/create_strategy.py
yuhanbolh/get_data.py
yuhanbolh/global_functions.py
yuhanbolh/mt5_ic_custom.py
yuhanbolh/mt5_trade.py
yuhanbolh/process_data.py
yuhanbolh/qmt_trade.py
yuhanbolh/send_email.py
yuhanbolh-0.6.1.dist-info/licenses/LICENSE
yuhanbolh-0.6.1.dist-info/METADATA
yuhanbolh-0.6.1.dist-info/WHEEL
yuhanbolh-0.6.1.dist-info/top_level.txt
yuhanbolh-0.6.1.dist-info/RECORD
